docorator/__init__.py
docorator/authentication_helper.py
docorator/docorator.py
docorator/markdown_converter.py
docorator-0.1.6.dist-info/METADATA
docorator-0.1.6.dist-info/WHEEL
docorator-0.1.6.dist-info/top_level.txt
docorator-0.1.6.dist-info/RECORD
