Metadata-Version: 2.4
Name: docorator
Version: 0.1.6
Summary: A Python library for interacting with Google Docs API with caching and logging
Author-email: Arved Klöhn <arved.kloehn@gmail.com>
Project-URL: Homepage, https://github.com/Redundando/docorator
Project-URL: Bug Tracker, https://github.com/Redundando/docorator/issues
Classifier: Programming Language :: Python :: 3
Classifier: License :: OSI Approved :: MIT License
Classifier: Operating System :: OS Independent
Requires-Python: >=3.7
Requires-Dist: google-auth
Requires-Dist: google-api-python-client
Requires-Dist: html2text
Requires-Dist: markdown
Requires-Dist: htmldocx
Requires-Dist: python-docx
Requires-Dist: bs4
Requires-Dist: cacherator
Requires-Dist: logorator
Requires-Dist: asyncio
